LICENSE
MANIFEST.in
README.md
requirements.txt
setup.cfg
setup.py
geather_1/__init__.py
geather_1/geather_1.py
geather_1.egg-info/PKG-INFO
geather_1.egg-info/SOURCES.txt
geather_1.egg-info/dependency_links.txt
geather_1.egg-info/not-zip-safe
geather_1.egg-info/top_level.txt
tests/test_geather_1.py