Metadata-Version: 2.1
Name: geather-1
Version: 0.0.1
Summary: just a try 
Home-page: https://github.com/giswr/geather_1
Author: Francis E. Oussou
Author-email: francisoussou@gmail.com
License: MIT license
Keywords: geather_1
Classifier: Development Status :: 2 - Pre-Alpha
Classifier: Intended Audience :: Developers
Classifier: License :: OSI Approved :: MIT License
Classifier: Natural Language :: English
Classifier: Programming Language :: Python :: 3
Classifier: Programming Language :: Python :: 3.7
Classifier: Programming Language :: Python :: 3.8
Classifier: Programming Language :: Python :: 3.9
Classifier: Programming Language :: Python :: 3.10
Requires-Python: >=3.7
License-File: LICENSE
